mpflash/__init__.py
mpflash/ask_input.py
mpflash/basicgit.py
mpflash/cli_add.py
mpflash/cli_download.py
mpflash/cli_flash.py
mpflash/cli_group.py
mpflash/cli_list.py
mpflash/cli_main.py
mpflash/common.py
mpflash/config.py
mpflash/connected.py
mpflash/downloaded.py
mpflash/errors.py
mpflash/list.py
mpflash/logger.py
mpflash/py.typed
mpflash/versions.py
mpflash/bootloader/__init__.py
mpflash/bootloader/activate.py
mpflash/bootloader/detect.py
mpflash/bootloader/manual.py
mpflash/bootloader/micropython.py
mpflash/bootloader/touch1200.py
mpflash/custom/__init__.py
mpflash/custom/add.py
mpflash/custom/copy.py
mpflash/custom/naming.py
mpflash/db/__init__.py
mpflash/db/boards_version.txt
mpflash/db/core.py
mpflash/db/gather_boards.py
mpflash/db/loader.py
mpflash/db/meta.py
mpflash/db/micropython_boards.zip
mpflash/db/models.py
mpflash/db/tools.py
mpflash/download/__init__.py
mpflash/download/from_web.py
mpflash/download/fwinfo.py
mpflash/download/jid.py
mpflash/flash/__init__.py
mpflash/flash/esp.py
mpflash/flash/stm32.py
mpflash/flash/stm32_dfu.py
mpflash/flash/worklist.py
mpflash/flash/uf2/__init__.py
mpflash/flash/uf2/boardid.py
mpflash/flash/uf2/linux.py
mpflash/flash/uf2/macos.py
mpflash/flash/uf2/uf2disk.py
mpflash/flash/uf2/windows.py
mpflash/mpboard_id/__init__.py
mpflash/mpboard_id/alternate.py
mpflash/mpboard_id/board_id.py
mpflash/mpboard_id/board_info.json
mpflash/mpboard_id/board_info.zip
mpflash/mpboard_id/known.py
mpflash/mpboard_id/resolve.py
mpflash/mpremoteboard/__init__.py
mpflash/mpremoteboard/mpy_fw_info.py
mpflash/mpremoteboard/runner.py
mpflash/vendor/board_database.py
mpflash/vendor/click_aliases.py
mpflash/vendor/dfu.py
mpflash/vendor/pydfu.py
mpflash/vendor/readme.md
mpflash/vendor/pico-universal-flash-nuke/LICENSE.txt
mpflash/vendor/pico-universal-flash-nuke/universal_flash_nuke.uf2
mpflash-1.26.8.dist-info/METADATA
mpflash-1.26.8.dist-info/WHEEL
mpflash-1.26.8.dist-info/entry_points.txt
mpflash-1.26.8.dist-info/licenses/LICENSE
mpflash-1.26.8.dist-info/RECORD
