Metadata-Version: 2.4
Name: mpflash
Version: 1.26.8
Summary: Flash and download tool for MicroPython firmwares
Project-URL: Homepage, https://github.com/Josverl/mpflash
Project-URL: Documentation, https://github.com/Josverl/mpflash/blob/main/README.md
Project-URL: Repository, https://github.com/Josverl/mpflash
Project-URL: Bug Tracker, https://github.com/Josverl/mpflash/issues
Author-email: Jos Verlinde <jos_verlinde@hotmail.com>
License: MIT
License-File: LICENSE
Keywords: MicroPython,UF2,download,esptool,firmware,flash
Classifier: Development Status :: 5 - Production/Stable
Classifier: Intended Audience :: Developers
Classifier: License :: OSI Approved :: MIT License
Classifier: Programming Language :: Python :: 3
Classifier: Programming Language :: Python :: 3.9
Classifier: Programming Language :: Python :: 3.10
Classifier: Programming Language :: Python :: 3.11
Classifier: Programming Language :: Python :: 3.12
Classifier: Programming Language :: Python :: Implementation :: CPython
Classifier: Programming Language :: Python :: Implementation :: MicroPython
Classifier: Topic :: Software Development :: Build Tools
Classifier: Topic :: System :: Hardware
Classifier: Topic :: Utilities
Requires-Python: >=3.9.2
Requires-Dist: beautifulsoup4>=4.12.3
Requires-Dist: bincopy>=20.0.0
Requires-Dist: blkinfo>=0.2.0
Requires-Dist: cache-to-disk>=2.0.0
Requires-Dist: cachetools>=5.3.0
Requires-Dist: esptool<5.0.0,>=4.7.0
Requires-Dist: inquirer>=3.2.4
Requires-Dist: jsonlines>=4.0.0
Requires-Dist: jsons>=1.6.3
Requires-Dist: libusb>=1.0.27; sys_platform == 'win32'
Requires-Dist: loguru>=0.7.2
Requires-Dist: mpremote>=1.22.0
Requires-Dist: packaging>=24.2
Requires-Dist: platformdirs>=4.2.0
Requires-Dist: psutil<8.0.0,>=7.0.0
Requires-Dist: pygithub>=2.1.1
Requires-Dist: pyusb>=1.2.1
Requires-Dist: pywin32>=310; sys_platform == 'win32'
Requires-Dist: requests>=2.31.0
Requires-Dist: rich-click>=1.8.1
Requires-Dist: sqlalchemy>=2.0.41
Requires-Dist: tenacity==9.0.0
Requires-Dist: tomli-w>=1.2.0
Requires-Dist: tomli>=2.2.1
Provides-Extra: dev
Requires-Dist: ipykernel>=6.29.5; extra == 'dev'
Requires-Dist: keyring>=25.6.0; extra == 'dev'
Requires-Dist: tornado>=6.5; extra == 'dev'
Provides-Extra: test
Requires-Dist: coverage<8.0.0,>=6.4.3; extra == 'test'
Requires-Dist: distro>=1.8.0; extra == 'test'
Requires-Dist: fasteners>=0.19; extra == 'test'
Requires-Dist: mock<6.0.0,>=4.0.3; extra == 'test'
Requires-Dist: pytest-cov>=6.0.0; extra == 'test'
Requires-Dist: pytest-github-actions-annotate-failures<0.4.0,>=0.1.7; extra == 'test'
Requires-Dist: pytest-json-report>=1.5.0; extra == 'test'
Requires-Dist: pytest-metadata<4.0.0,>=2.0.2; extra == 'test'
Requires-Dist: pytest-mock>=3.10.0; extra == 'test'
Requires-Dist: pytest<9.0.0,>=7.1.2; extra == 'test'
